geoip2_tools/__init__.py
geoip2_tools/database.py
geoip2_tools/exceptions.py
geoip2_tools/management.py
geoip2_tools/manager.py
geoip2_tools/utils.py
geoip2_tools/tests/__init__.py
geoip2_tools/tests/test_geoip2_tools.py
geoip2_tools-0.1.1.dist-info/LICENSE
geoip2_tools-0.1.1.dist-info/METADATA
geoip2_tools-0.1.1.dist-info/WHEEL
geoip2_tools-0.1.1.dist-info/entry_points.txt
geoip2_tools-0.1.1.dist-info/top_level.txt
geoip2_tools-0.1.1.dist-info/RECORD
