Metadata-Version: 2.1
Name: geoip2-tools
Version: 0.1.1
Summary: Automatic updates and administration of MaxMind GeoIP2 databases.
Home-page: https://github.com/Nekmo/geoip2-tools/
Author: Nekmo
Author-email: contacto@nekmo.com
License: MIT
Download-URL: https://github.com/Nekmo/geoip2-tools/archive/master.zip
Keywords: geoip2-tools
Platform: linux
Classifier: License :: OSI Approved :: MIT License
Classifier: Programming Language :: Python :: 3.8
Classifier: Programming Language :: Python :: 3.7
Classifier: Programming Language :: Python :: 3.5
Classifier: Programming Language :: Python :: 3 :: Only
Classifier: Programming Language :: Python :: 3.6
Classifier: Operating System :: POSIX
Classifier: Operating System :: POSIX :: Linux
Classifier: Natural Language :: English
Classifier: Development Status :: 5 - Production/Stable
Requires-Dist: click (>=6.0)
Requires-Dist: requests
Requires-Dist: geoip2
